rlvoice/__init__.py
rlvoice/driver.py
rlvoice/engine.py
rlvoice/voice.py
rlvoice/drivers/__init__.py
rlvoice/drivers/_espeak.py
rlvoice/drivers/coqui_ai_tts.py
rlvoice/drivers/dummy.py
rlvoice/drivers/espeak.py
rlvoice/drivers/nsss.py
rlvoice/drivers/sapi5.py
rlvoice_1-1.3.4.dist-info/LICENSE
rlvoice_1-1.3.4.dist-info/METADATA
rlvoice_1-1.3.4.dist-info/WHEEL
rlvoice_1-1.3.4.dist-info/top_level.txt
rlvoice_1-1.3.4.dist-info/RECORD
