Metadata-Version: 2.1
Name: rlvoice-1
Version: 1.3.4
Summary: Text to Speech (TTS) library for Python 3. Works without internet connection or delay. Supports multiple TTS engines, including Sapi5, nsss, and espeak.
Home-page: https://github.com/Akul-AI/rlvoice-1
Author: AkulAI
Author-email: akulgoel2010@gmail.com
Keywords: rlvoice,pyttsx,ivona,pyttsx for python3,TTS for python3,rlvoice,text to speech for python,tts,text to speech,speech,speech synthesis,offline text to speech,offline tts,gtts
Classifier: Intended Audience :: End Users/Desktop
Classifier: Intended Audience :: Developers
Classifier: Intended Audience :: Information Technology
Classifier: Intended Audience :: System Administrators
Classifier: Operating System :: MacOS :: MacOS X
Classifier: Operating System :: Microsoft :: Windows
Classifier: Operating System :: POSIX
Classifier: License :: OSI Approved :: Mozilla Public License 2.0 (MPL 2.0)
Classifier: Programming Language :: Python :: 3
Classifier: Programming Language :: Python :: 3.5
Classifier: Programming Language :: Python :: 3.6
Classifier: Programming Language :: Python :: 3.7
Classifier: Programming Language :: Python :: 3.8
Classifier: Programming Language :: Python :: 3.9
Classifier: Programming Language :: Python :: 3.10
Classifier: Programming Language :: Python :: 3.11
Classifier: Programming Language :: Python :: 3.12
Classifier: Programming Language :: Python :: 3.13
License-File: LICENSE
Requires-Dist: six
Requires-Dist: pyobjc <=9.0.1,>=9.0.1 ; platform_system == "Darwin"
Requires-Dist: comtypes ; platform_system == "Windows"
Requires-Dist: pypiwin32 ; platform_system == "Windows"
Requires-Dist: pywin32 ; platform_system == "Windows"
